pyprotolinc/__init__.py
pyprotolinc/__main__.py
pyprotolinc/_actuarial.cp311-win_amd64.pyd
pyprotolinc/api.py
pyprotolinc/main.py
pyprotolinc/portfolio.py
pyprotolinc/product.py
pyprotolinc/results.py
pyprotolinc/runner.py
pyprotolinc/utils.py
pyprotolinc/actuarial/__init__.py
pyprotolinc/actuarial/crisk_factors.pxd
pyprotolinc/actuarial/portfolio.pxd
pyprotolinc/actuarial/providers.pxd
pyprotolinc/actuarial/valuation.cpp
pyprotolinc/actuarial/valuation.pyx
pyprotolinc/actuarial/c_src/.gitignore
pyprotolinc/actuarial/c_src/CMakeLists.txt
pyprotolinc/actuarial/c_src/Doxyfile
pyprotolinc/actuarial/c_src/build_and_run_main.bat
pyprotolinc/actuarial/c_src/build_and_run_tests.bat
pyprotolinc/actuarial/c_src/cmain.cpp
pyprotolinc/actuarial/c_src/conanfile.txt
pyprotolinc/actuarial/c_src/cresult.xlsx
pyprotolinc/actuarial/c_src/cresults.csv
pyprotolinc/actuarial/c_src/datums_calc.xlsx
pyprotolinc/actuarial/c_src/my_log.txt
pyprotolinc/actuarial/c_src/modules/assumption_sets.h
pyprotolinc/actuarial/c_src/modules/c_valuation.cpp
pyprotolinc/actuarial/c_src/modules/c_valuation.h
pyprotolinc/actuarial/c_src/modules/log.h
pyprotolinc/actuarial/c_src/modules/payments.h
pyprotolinc/actuarial/c_src/modules/portfolio.h
pyprotolinc/actuarial/c_src/modules/products.h
pyprotolinc/actuarial/c_src/modules/providers.h
pyprotolinc/actuarial/c_src/modules/record_projector.h
pyprotolinc/actuarial/c_src/modules/risk_factors.h
pyprotolinc/actuarial/c_src/modules/run_config.h
pyprotolinc/actuarial/c_src/modules/run_result.h
pyprotolinc/actuarial/c_src/modules/runner.h
pyprotolinc/actuarial/c_src/modules/time_axis.h
pyprotolinc/actuarial/c_src/modules/utils.h
pyprotolinc/assumptions/__init__.py
pyprotolinc/assumptions/dav2004r.py
pyprotolinc/assumptions/dav2008t.py
pyprotolinc/assumptions/iohelpers.py
pyprotolinc/assumptions/providers.py
pyprotolinc/assumptions/tables.py
pyprotolinc/models/__init__.py
pyprotolinc/models/model_config.py
pyprotolinc/models/model_multistate_generic.py
PyProtolinc-0.1.7.dist-info/LICENSE
PyProtolinc-0.1.7.dist-info/METADATA
PyProtolinc-0.1.7.dist-info/WHEEL
PyProtolinc-0.1.7.dist-info/entry_points.txt
PyProtolinc-0.1.7.dist-info/top_level.txt
PyProtolinc-0.1.7.dist-info/RECORD
